django_svg_icons-0.1.2.dist-info/DESCRIPTION.rst
django_svg_icons-0.1.2.dist-info/METADATA
django_svg_icons-0.1.2.dist-info/RECORD
django_svg_icons-0.1.2.dist-info/WHEEL
django_svg_icons-0.1.2.dist-info/metadata.json
django_svg_icons-0.1.2.dist-info/top_level.txt
svg_icons/__init__.py
svg_icons/readers/__init__.py
svg_icons/readers/base.py
svg_icons/readers/icomoon.py
svg_icons/templates/svg_icons/icon.html
svg_icons/templatetags/__init__.py
svg_icons/templatetags/svg_icons.py
