Metadata-Version: 2.0
Name: django-svg-icons
Version: 0.1.2
Summary: Django SVG Icons made easy
Home-page: https://github.com/mikedingjan/django-svg-icons
Author: Mike Dingjan
Author-email: mike@mikedingjan.nl
License: Apache License
Keywords: SVG icons,django icons
Platform: osx
Platform: linux
Classifier: Development Status :: 4 - Beta
Classifier: Environment :: Web Environment
Classifier: Framework :: Django
Classifier: Framework :: Django :: 1.8
Classifier: Framework :: Django :: 1.9
Classifier: Framework :: Django :: 1.10
Classifier: Intended Audience :: Developers
Classifier: Programming Language :: Python
Classifier: Programming Language :: Python :: 2
Classifier: Programming Language :: Python :: 2.7
Classifier: Programming Language :: Python :: 3
Classifier: Programming Language :: Python :: 3.3
Classifier: Programming Language :: Python :: 3.4
Classifier: Programming Language :: Python :: 3.5
